netqmpi/__init__.py
netqmpi/runtime/__init__.py
netqmpi/runtime/cli.py
netqmpi/sdk/__init__.py
netqmpi/sdk/communicator.py
netqmpi/sdk/external.py
netqmpi-0.1.0.dist-info/METADATA
netqmpi-0.1.0.dist-info/WHEEL
netqmpi-0.1.0.dist-info/entry_points.txt
netqmpi-0.1.0.dist-info/top_level.txt
netqmpi-0.1.0.dist-info/RECORD
